{
    "0": {
        "ID": "0",
        "Name": "START-COMENZAR",
        "Alias": "COMENZAR",
        "SensorID": 255,
        "SensorActive": false,
        "ScreenID": 1,
        "Cost": 0,
        "EnemyProbability": 0,
        "ResetEnemyProbability": 0,
        "DeathProbability": 0,
        "Description": "",
        "DescriptionActionFailed": "",
        "HideOnWaterLevelHigh": 0,
        "HideOnFearLevelHigh": 0,
        "HideWithFlashlightOff": 0
    },
    "1": {
        "ID": "1",
        "Name": "S01P01-LEVANTARSE",
        "Alias": "LEVANTARSE",
        "SensorID": 0,
        "SensorActive": true,
        "ScreenID": 2,
        "Cost": 0,
        "EnemyProbability": 0,
        "ResetEnemyProbability": 0,
        "DeathProbability": 0,
        "Description": "TE LEVANTAS. ESCUCHAS EL RUIDO DEL AGUA. EL TIEMPO COMIENZA A CORRER",
        "DescriptionActionFailed": "",
        "HideOnWaterLevelHigh": 0,
        "HideOnFearLevelHigh": 0,
        "HideWithFlashlightOff": 0
    },
    "2": {
        "ID": "2",
        "Name": "S01P02-GRITARPORAYUDA",
        "Alias": "GRITAR POR AYUDA",
        "SensorID": 1,
        "SensorActive": true,
        "ScreenID": 3,
        "Cost": 0,
        "EnemyProbability": 0,
        "ResetEnemyProbability": 0,
        "DeathProbability": 0,
        "Description": "GRITAS POR AYUDA. ESTAS SOLO. TENES MUEDO EN LA OSCURIDAD.",
        "DescriptionActionFailed": "",
        "HideOnWaterLevelHigh": 0,
        "HideOnFearLevelHigh": 0,
        "HideWithFlashlightOff": 0
    },
    "3": {
        "ID": "3",
        "Name": "LINTERNACORAZON-TOGGLE",
        "Alias": "LINTERNA",
        "SensorID": 6,
        "SensorActive": true,
        "ScreenID": 255,
        "Cost": 5,
        "EnemyProbability": 0,
        "ResetEnemyProbability": 0,
        "DeathProbability": 0,
        "Description": "PRENDO O APAGO LA LINTERNA Y CORAZON",
        "DescriptionActionFailed": "",
        "HideOnWaterLevelHigh": 0,
        "HideOnFearLevelHigh": 0,
        "HideWithFlashlightOff": 0
    },
    "4": {
        "ID": "4",
        "Name": "S01P03-EXPLORAR",
        "Alias": "EXPLORAR",
        "SensorID": 255,
        "SensorActive": false,
        "ScreenID": 4,
        "Cost": 5,
        "EnemyProbability": 0,
        "ResetEnemyProbability": 0,
        "DeathProbability": 0,
        "Description": "EXPLORAS EL LUGAR. ESTAS ENCERRADO. PARECE HABER ROCAS BLOQUEANDO EL CAMINO.",
        "DescriptionActionFailed": "",
        "HideOnWaterLevelHigh": 0,
        "HideOnFearLevelHigh": 0,
        "HideWithFlashlightOff": 0
    },
    "5": {
        "ID": "5",
        "Name": "S01P04-ROCASLINTERNA",
        "Alias": "ILUMINAR ROCAS (LINTERNA)",
        "SensorID": 255,
        "SensorActive": false,
        "ScreenID": 5,
        "Cost": 10,
        "EnemyProbability": 0,
        "ResetEnemyProbability": 0,
        "DeathProbability": 0,
        "Description": "LAS ROCAS PARECEN SEGUIR UN PATRON",
        "DescriptionActionFailed": "",
        "HideOnWaterLevelHigh": 0,
        "HideOnFearLevelHigh": 0,
        "HideWithFlashlightOff": 1
    },
    "6": {
        "ID": "6",
        "Name": "S01P04-ROCASOSCURIDAD",
        "Alias": "TOCAR ROCAS (OSCURIDAD)",
        "SensorID": 255,
        "SensorActive": false,
        "ScreenID": 7,
        "Cost": 10,
        "EnemyProbability": 0,
        "ResetEnemyProbability": 0,
        "DeathProbability": 0,
        "Description": "LAS ROCAS SON DE DIFERENTE TAMAÑO",
        "DescriptionActionFailed": "",
        "HideOnWaterLevelHigh": 0,
        "HideOnFearLevelHigh": 0,
        "HideWithFlashlightOff": 0
    },
    "7": {
        "ID": "7",
        "Name": "S01P05-EXTRAERROCA",
        "Alias": "EXTRAER ROCA",
        "SensorID": 255,
        "SensorActive": false,
        "ScreenID": 6,
        "Cost": 0,
        "EnemyProbability": 0,
        "ResetEnemyProbability": 0,
        "DeathProbability": 13,
        "Description": "EXPLORASTE Y ENCONTRASTE ALGO",
        "DescriptionActionFailed": "EXPLORASTE Y SE TE CALLERON LAS ROCAS EN LA CABEZA.\nMUERTE.",
        "HideOnWaterLevelHigh": 0,
        "HideOnFearLevelHigh": 0,
        "HideWithFlashlightOff": 0
    },
    "8": {
        "ID": "8",
        "Name": "S01P05-IGNORAR",
        "Alias": "IGNORAR",
        "SensorID": 255,
        "SensorActive": false,
        "ScreenID": 7,
        "Cost": 0,
        "EnemyProbability": 0,
        "ResetEnemyProbability": 0,
        "DeathProbability": 0,
        "Description": "MEJOR NO TENTAR AL DESTINO. SIGO CON EL JUEGO.",
        "DescriptionActionFailed": "",
        "HideOnWaterLevelHigh": 0,
        "HideOnFearLevelHigh": 0,
        "HideWithFlashlightOff": 0
    },
    "9": {
        "ID": "9",
        "Name": "S01P06-CONTINUAR",
        "Alias": "CONTINUAR",
        "SensorID": 255,
        "SensorActive": false,
        "ScreenID": 7,
        "Cost": 0,
        "EnemyProbability": 0,
        "ResetEnemyProbability": 0,
        "DeathProbability": 0,
        "Description": "SEGUIS EL FLUJO DEL JUEGO",
        "DescriptionActionFailed": "",
        "HideOnWaterLevelHigh": 0,
        "HideOnFearLevelHigh": 0,
        "HideWithFlashlightOff": 0
    },
    "10": {
        "ID": "10",
        "Name": "S01P07-ROCASSEGURO",
        "Alias": "RETIRAR ROCAS (SEGURO)",
        "SensorID": 255,
        "SensorActive": false,
        "ScreenID": 8,
        "Cost": 20,
        "EnemyProbability": 0,
        "ResetEnemyProbability": 0,
        "DeathProbability": 0,
        "Description": "RETIRASTE LAS ROCAS DE MANERA SEGURA, SEGUIS CAMINO.",
        "DescriptionActionFailed": "A PESAR DE LA CAUTELA, SE TE CAYERON LAS ROCAS ENCIMA. MUERTE.",
        "HideOnWaterLevelHigh": 0,
        "HideOnFearLevelHigh": 0,
        "HideWithFlashlightOff": 0
    },
    "11": {
        "ID": "11",
        "Name": "S01P07-ROCASRAPIDO",
        "Alias": "ATRAVESAR ROCAS (RAPIDO)",
        "SensorID": 1,
        "SensorActive": true,
        "ScreenID": 8,
        "Cost": 10,
        "EnemyProbability": 0,
        "ResetEnemyProbability": 0,
        "DeathProbability": 100,
        "Description": "EMPUJASTE LAS ROCAS Y PASASTE POR UN HUECO",
        "DescriptionActionFailed": "RAPIDO Y FURIOSO FUE EL DERRUMBE SOBRE TU CUERPO. MUERTE.",
        "HideOnWaterLevelHigh": 0,
        "HideOnFearLevelHigh": 0,
        "HideWithFlashlightOff": 0
    },
    "12": {
        "ID": "12",
        "Name": "S02P01-CONTINUAR",
        "Alias": "CONTINUAR",
        "SensorID": 1,
        "SensorActive": true,
        "ScreenID": 9,
        "Cost": 0,
        "EnemyProbability": 0,
        "ResetEnemyProbability": 0,
        "DeathProbability": 0,
        "Description": "Sigue el flujo del juego y activa el sensor corazon para explicar la mecanica DESCANSAR",
        "DescriptionActionFailed": "",
        "HideOnWaterLevelHigh": 0,
        "HideOnFearLevelHigh": 0,
        "HideWithFlashlightOff": 0
    },
    "13": {
        "ID": "13",
        "Name": "S02P02-DESCANSAR",
        "Alias": "DESCANSAR",
        "SensorID": 1,
        "SensorActive": false,
        "ScreenID": 10,
        "Cost": 10,
        "EnemyProbability": 0,
        "ResetEnemyProbability": 0,
        "DeathProbability": 0,
        "Description": "Apaga el sensor Heart a un costo (2 x linterna)",
        "DescriptionActionFailed": "",
        "HideOnWaterLevelHigh": 0,
        "HideOnFearLevelHigh": 0,
        "HideWithFlashlightOff": 0
    },
    "14": {
        "ID": "14",
        "Name": "S02P02-CORRER",
        "Alias": "CORRER HACIA LA PROXIMA SALIDA",
        "SensorID": 255,
        "SensorActive": false,
        "ScreenID": 255,
        "Cost": 0,
        "EnemyProbability": 0,
        "ResetEnemyProbability": 0,
        "DeathProbability": 255,
        "Description": "",
        "DescriptionActionFailed": "Corres hacia lo profundo de la caverna. En la desesperacion, no es posible una solucion. \n\nMUERTE",
        "HideOnWaterLevelHigh": 0,
        "HideOnFearLevelHigh": 0,
        "HideWithFlashlightOff": 0
    },
    "15": {
        "ID": "15",
        "Name": "DESCANSAR",
        "Alias": "DESCANSAR",
        "SensorID": 1,
        "SensorActive": false,
        "ScreenID": 255,
        "Cost": 10,
        "EnemyProbability": 0,
        "ResetEnemyProbability": 0,
        "DeathProbability": 0,
        "Description": "",
        "DescriptionActionFailed": "",
        "HideOnWaterLevelHigh": 0,
        "HideOnFearLevelHigh": 0,
        "HideWithFlashlightOff": 0
    },
    "16": {
        "ID": "16",
        "Name": "S02P03-ANALIZARMARCAS",
        "Alias": "ANALIZAR MARCAS",
        "SensorID": 255,
        "SensorActive": false,
        "ScreenID": 11,
        "Cost": 10,
        "EnemyProbability": 0,
        "ResetEnemyProbability": 0,
        "DeathProbability": 0,
        "Description": "Analizas las marcas",
        "DescriptionActionFailed": "",
        "HideOnWaterLevelHigh": 0,
        "HideOnFearLevelHigh": 0,
        "HideWithFlashlightOff": 0
    },
    "17": {
        "ID": "17",
        "Name": "S02P03-ELEGIR SALIDA",
        "Alias": "ELEGIR SALIDA",
        "SensorID": 255,
        "SensorActive": false,
        "ScreenID": 13,
        "Cost": 0,
        "EnemyProbability": 0,
        "ResetEnemyProbability": 0,
        "DeathProbability": 0,
        "Description": "Continua el flujo del juego",
        "DescriptionActionFailed": "",
        "HideOnWaterLevelHigh": 0,
        "HideOnFearLevelHigh": 0,
        "HideWithFlashlightOff": 0
    },
    "18": {
        "ID": "18",
        "Name": "S02P03-EXPLORARREFLEJO",
        "Alias": "EXPLORAR REFLEJO",
        "SensorID": 255,
        "SensorActive": false,
        "ScreenID": 12,
        "Cost": 10,
        "EnemyProbability": 0,
        "ResetEnemyProbability": 0,
        "DeathProbability": 0,
        "Description": "Procedes a explorar el reflejo",
        "DescriptionActionFailed": "",
        "HideOnWaterLevelHigh": 0,
        "HideOnFearLevelHigh": 0,
        "HideWithFlashlightOff": 1
    },
    "19": {
        "ID": "19",
        "Name": "S02P0456-VOLVER",
        "Alias": "VOLVER",
        "SensorID": 255,
        "SensorActive": false,
        "ScreenID": 10,
        "Cost": 0,
        "EnemyProbability": 0,
        "ResetEnemyProbability": 0,
        "DeathProbability": 0,
        "Description": "Volver a pantalla anterior",
        "DescriptionActionFailed": "",
        "HideOnWaterLevelHigh": 0,
        "HideOnFearLevelHigh": 0,
        "HideWithFlashlightOff": 0
    },
    "20": {
        "ID": "20",
        "Name": "S02P06-ANALIZARSALIDAS",
        "Alias": "ANALIZAR SALIDAS",
        "SensorID": 255,
        "SensorActive": false,
        "ScreenID": 14,
        "Cost": 20,
        "EnemyProbability": 0,
        "ResetEnemyProbability": 0,
        "DeathProbability": 0,
        "Description": "Procedes a analizar salidas",
        "DescriptionActionFailed": "",
        "HideOnWaterLevelHigh": 0,
        "HideOnFearLevelHigh": 1,
        "HideWithFlashlightOff": 0
    },
    "21": {
        "ID": "21",
        "Name": "S02P06-PROBARSUERTE",
        "Alias": "PROBAR SUERTE",
        "SensorID": 1,
        "SensorActive": true,
        "ScreenID": 15,
        "Cost": 10,
        "EnemyProbability": 0,
        "ResetEnemyProbability": 0,
        "DeathProbability": 170,
        "Description": "Accion Exitosa: Lleva a proxima sala",
        "DescriptionActionFailed": "Accion Fallida: Te perdes por siempre",
        "HideOnWaterLevelHigh": 0,
        "HideOnFearLevelHigh": 0,
        "HideWithFlashlightOff": 0
    },
    "22": {
        "ID": "22",
        "Name": "S02P07-SALIDADERECHA",
        "Alias": "SALIDA DERECHA",
        "SensorID": 255,
        "SensorActive": false,
        "ScreenID": 255,
        "Cost": 10,
        "EnemyProbability": 0,
        "ResetEnemyProbability": 0,
        "DeathProbability": 85,
        "Description": "Accion Exitosa: Elegis mal pero vuelve a pantalla",
        "DescriptionActionFailed": "Accion Fallida: Elegis mal y te perdes",
        "HideOnWaterLevelHigh": 0,
        "HideOnFearLevelHigh": 0,
        "HideWithFlashlightOff": 0
    },
    "23": {
        "ID": "23",
        "Name": "S02P07-SALIDACENTRO",
        "Alias": "SALIDA CENTRO",
        "SensorID": 255,
        "SensorActive": false,
        "ScreenID": 255,
        "Cost": 10,
        "EnemyProbability": 0,
        "ResetEnemyProbability": 0,
        "DeathProbability": 85,
        "Description": "Accion Exitosa: Elegis mal pero vuelve a pantalla",
        "DescriptionActionFailed": "Accion Fallida: Elegis mal y te perdes\n",
        "HideOnWaterLevelHigh": 0,
        "HideOnFearLevelHigh": 0,
        "HideWithFlashlightOff": 0
    },
    "24": {
        "ID": "24",
        "Name": "S02P07-SALIDAIZQUIERDA",
        "Alias": "SALIDA IZQUIERDA",
        "SensorID": 255,
        "SensorActive": false,
        "ScreenID": 15,
        "Cost": 10,
        "EnemyProbability": 0,
        "ResetEnemyProbability": 0,
        "DeathProbability": 0,
        "Description": "Elegis exitosamente y pasas de Sala",
        "DescriptionActionFailed": "",
        "HideOnWaterLevelHigh": 0,
        "HideOnFearLevelHigh": 0,
        "HideWithFlashlightOff": 0
    },
    "25": {
        "ID": "25",
        "Name": "S02P07-VOLVER",
        "Alias": "VOLVER",
        "SensorID": 255,
        "SensorActive": false,
        "ScreenID": 13,
        "Cost": 10,
        "EnemyProbability": 0,
        "ResetEnemyProbability": 0,
        "DeathProbability": 0,
        "Description": "Volver a pantalla anterior",
        "DescriptionActionFailed": "",
        "HideOnWaterLevelHigh": 0,
        "HideOnFearLevelHigh": 0,
        "HideWithFlashlightOff": 0
    },
    "26": {
        "ID": "26",
        "Name": "S03P01-AVANZARCUIDADO",
        "Alias": "AVANZAR CON CUIDADO",
        "SensorID": 2,
        "SensorActive": false,
        "ScreenID": 16,
        "Cost": 10,
        "EnemyProbability": 0,
        "ResetEnemyProbability": 0,
        "DeathProbability": 0,
        "Description": "Avanzas con cuidado, la linterna comienza a parpadear y se apaga. El ruido de tus pisadas retumba mas de lo que deberia. El pasillo se hace mas angosto. ",
        "DescriptionActionFailed": "",
        "HideOnWaterLevelHigh": 0,
        "HideOnFearLevelHigh": 1,
        "HideWithFlashlightOff": 0
    },
    "27": {
        "ID": "27",
        "Name": "S03P01-AVANZARCORRIENDO",
        "Alias": "AVANZAR CORRIENDO",
        "SensorID": 2,
        "SensorActive": false,
        "ScreenID": 16,
        "Cost": 5,
        "EnemyProbability": 0,
        "ResetEnemyProbability": 0,
        "DeathProbability": 127,
        "Description": "Comienzas a correr por el pasillo, sintiendo un temblor que va en crecimiento. La linterna comienza a parpadear y se apaga. El pasillo se va haciendo mas angosto.\nLlegas a la proxima instancia\n",
        "DescriptionActionFailed": "Comienzas a correr por el pasillo, sintiendo un temblor que va en crecimiento. La linterna comienza a parpadear y se apaga. El pasillo se va haciendo mas angosto.\nSe te derrumba la caverna encima",
        "HideOnWaterLevelHigh": 0,
        "HideOnFearLevelHigh": 0,
        "HideWithFlashlightOff": 0
    },
    "28": {
        "ID": "28",
        "Name": "S03P02-ENCENDERLINTERNA",
        "Alias": "LINTERNA",
        "SensorID": 2,
        "SensorActive": true,
        "ScreenID": 17,
        "Cost": 5,
        "EnemyProbability": 0,
        "ResetEnemyProbability": 0,
        "DeathProbability": 0,
        "Description": "Iluminas hacia atras. Algo parece moverse, pero no hay nada alli. El encierro juega una mala pasada con tus sentidos.",
        "DescriptionActionFailed": "",
        "HideOnWaterLevelHigh": 0,
        "HideOnFearLevelHigh": 0,
        "HideWithFlashlightOff": 0
    },
    "29": {
        "ID": "29",
        "Name": "S03P02-MANTENERAPAGADA",
        "Alias": "MANTENER APAGADA",
        "SensorID": 255,
        "SensorActive": false,
        "ScreenID": 255,
        "Cost": 5,
        "EnemyProbability": 0,
        "ResetEnemyProbability": 0,
        "DeathProbability": 0,
        "Description": "A veces es mejor no buscar aquello que no queremos encontrar.",
        "DescriptionActionFailed": "",
        "HideOnWaterLevelHigh": 0,
        "HideOnFearLevelHigh": 0,
        "HideWithFlashlightOff": 0
    },
    "30": {
        "ID": "30",
        "Name": "S03P03-ILUMINARTECHO",
        "Alias": "ILUMINAR TECHO",
        "SensorID": 255,
        "SensorActive": false,
        "ScreenID": 18,
        "Cost": 10,
        "EnemyProbability": 0,
        "ResetEnemyProbability": 0,
        "DeathProbability": 0,
        "Description": "Procedes a iluminar el techo\n\n",
        "DescriptionActionFailed": "",
        "HideOnWaterLevelHigh": 0,
        "HideOnFearLevelHigh": 0,
        "HideWithFlashlightOff": 1
    },
    "31": {
        "ID": "31",
        "Name": "S03P03-ELEGIRCAMINO",
        "Alias": "ELEGIR CAMINO",
        "SensorID": 255,
        "SensorActive": false,
        "ScreenID": 19,
        "Cost": 0,
        "EnemyProbability": 0,
        "ResetEnemyProbability": 0,
        "DeathProbability": 0,
        "Description": "Procedes a elegir el camino\n\n",
        "DescriptionActionFailed": "",
        "HideOnWaterLevelHigh": 0,
        "HideOnFearLevelHigh": 0,
        "HideWithFlashlightOff": 0
    },
    "32": {
        "ID": "32",
        "Name": "S03P04-VOLVER",
        "Alias": "VOLVER",
        "SensorID": 255,
        "SensorActive": false,
        "ScreenID": 17,
        "Cost": 0,
        "EnemyProbability": 0,
        "ResetEnemyProbability": 0,
        "DeathProbability": 0,
        "Description": "Continua el flujo del juego\n\n",
        "DescriptionActionFailed": "",
        "HideOnWaterLevelHigh": 0,
        "HideOnFearLevelHigh": 0,
        "HideWithFlashlightOff": 0
    },
    "33": {
        "ID": "33",
        "Name": "S03P05-ELEGIRDERECHA",
        "Alias": "ELEGIR DERECHA",
        "SensorID": 255,
        "SensorActive": false,
        "ScreenID": 20,
        "Cost": 10,
        "EnemyProbability": 0,
        "ResetEnemyProbability": 0,
        "DeathProbability": 1,
        "Description": "Elegis el camino correcto\nAccion Exitosa: Pasaste sin problema",
        "DescriptionActionFailed": "Elegis el camino correcto\nAccion Fallida: El miedo te hizo hacer mas ruido. Se te cae una estalactiva encima. Muerte",
        "HideOnWaterLevelHigh": 0,
        "HideOnFearLevelHigh": 0,
        "HideWithFlashlightOff": 0
    },
    "34": {
        "ID": "34",
        "Name": "S03P05-ELEGIRIZQUIERDA",
        "Alias": "ELEGIRIZQUIERDA",
        "SensorID": 1,
        "SensorActive": true,
        "ScreenID": 20,
        "Cost": 10,
        "EnemyProbability": 0,
        "ResetEnemyProbability": 0,
        "DeathProbability": 127,
        "Description": "Elegis el camino incorrecto\nAccion Exitosa: Diste un paso, se cayo la estalactita y te salvaste. Pasaste por el otro lado",
        "DescriptionActionFailed": "Elegis el camino incorrecto\nAccion Fallida: Se te cae una estalactiva encima. Muerte",
        "HideOnWaterLevelHigh": 0,
        "HideOnFearLevelHigh": 0,
        "HideWithFlashlightOff": 0
    },
    "35": {
        "ID": "35",
        "Name": "S03P06-ILUMINARTECHO",
        "Alias": "ILUMINAR TECHO",
        "SensorID": 255,
        "SensorActive": false,
        "ScreenID": 21,
        "Cost": 10,
        "EnemyProbability": 0,
        "ResetEnemyProbability": 0,
        "DeathProbability": 0,
        "Description": "Procedes a iluminar el techo\n\n",
        "DescriptionActionFailed": "",
        "HideOnWaterLevelHigh": 0,
        "HideOnFearLevelHigh": 0,
        "HideWithFlashlightOff": 1
    },
    "36": {
        "ID": "36",
        "Name": "S03P06-ELEGIRCAMINO",
        "Alias": "ELEGIR CAMINO",
        "SensorID": 255,
        "SensorActive": false,
        "ScreenID": 23,
        "Cost": 0,
        "EnemyProbability": 0,
        "ResetEnemyProbability": 0,
        "DeathProbability": 0,
        "Description": "",
        "DescriptionActionFailed": "",
        "HideOnWaterLevelHigh": 0,
        "HideOnFearLevelHigh": 0,
        "HideWithFlashlightOff": 0
    },
    "37": {
        "ID": "37",
        "Name": "S03P07-ILUMINARMARCAS",
        "Alias": "ILUMINAR MARCAS",
        "SensorID": 255,
        "SensorActive": false,
        "ScreenID": 22,
        "Cost": 10,
        "EnemyProbability": 0,
        "ResetEnemyProbability": 0,
        "DeathProbability": 0,
        "Description": "Procedes a iluminar las marcas\n\n",
        "DescriptionActionFailed": "",
        "HideOnWaterLevelHigh": 0,
        "HideOnFearLevelHigh": 0,
        "HideWithFlashlightOff": 0
    },
    "38": {
        "ID": "38",
        "Name": "S03P07-VOLVER",
        "Alias": "VOLVER",
        "SensorID": 255,
        "SensorActive": false,
        "ScreenID": 20,
        "Cost": 0,
        "EnemyProbability": 0,
        "ResetEnemyProbability": 0,
        "DeathProbability": 0,
        "Description": "Vuelve a pantalla anterior",
        "DescriptionActionFailed": "",
        "HideOnWaterLevelHigh": 0,
        "HideOnFearLevelHigh": 0,
        "HideWithFlashlightOff": 0
    },
    "39": {
        "ID": "39",
        "Name": "S03P08-VOLVER",
        "Alias": "VOLVER",
        "SensorID": 255,
        "SensorActive": false,
        "ScreenID": 21,
        "Cost": 0,
        "EnemyProbability": 1,
        "ResetEnemyProbability": 0,
        "DeathProbability": 0,
        "Description": "Volves a la pantalla anterior",
        "DescriptionActionFailed": "",
        "HideOnWaterLevelHigh": 0,
        "HideOnFearLevelHigh": 0,
        "HideWithFlashlightOff": 0
    },
    "40": {
        "ID": "40",
        "Name": "S03P09-ELEGIRDERECHA",
        "Alias": "ELEGIR DERECHA",
        "SensorID": 255,
        "SensorActive": false,
        "ScreenID": 24,
        "Cost": 10,
        "EnemyProbability": 0,
        "ResetEnemyProbability": 1,
        "DeathProbability": 1,
        "Description": "Elegis el camino correcto\nAccion Exitosa: Pasaste sin problema. Avanzas en el pasillo y salis de la sala. Deseas nunca tener que volver por aca.",
        "DescriptionActionFailed": "Elegis el camino correcto\nAccion Fallida: El miedo te hizo hacer mas ruido. La caverna muestra que no todo es lo que parece",
        "HideOnWaterLevelHigh": 0,
        "HideOnFearLevelHigh": 0,
        "HideWithFlashlightOff": 0
    },
    "41": {
        "ID": "41",
        "Name": "S03P09-ELEGIRIZQUIERDA",
        "Alias": "ELEGIR IZQUIERDA",
        "SensorID": 255,
        "SensorActive": false,
        "ScreenID": 24,
        "Cost": 10,
        "EnemyProbability": 0,
        "ResetEnemyProbability": 1,
        "DeathProbability": 1,
        "Description": "Elegis el camino correcto\nAccion Exitosa: Pasaste sin problema. Avanzas en el pasillo y salis de la sala. Deseas nunca tener que volver por aca.",
        "DescriptionActionFailed": "Elegis el camino correcto\nAccion Fallida: El miedo te hizo hacer mas ruido. La caverna muestra que no todo es lo que parece",
        "HideOnWaterLevelHigh": 0,
        "HideOnFearLevelHigh": 0,
        "HideWithFlashlightOff": 0
    },
    "42": {
        "ID": "42",
        "Name": "S04P01-DESCENDER",
        "Alias": "DESCENDER",
        "SensorID": 255,
        "SensorActive": false,
        "ScreenID": 25,
        "Cost": 10,
        "EnemyProbability": 0,
        "ResetEnemyProbability": 0,
        "DeathProbability": 0,
        "Description": "Te tomas un instante para analizar la situacion.",
        "DescriptionActionFailed": "",
        "HideOnWaterLevelHigh": 0,
        "HideOnFearLevelHigh": 0,
        "HideWithFlashlightOff": 1
    },
    "43": {
        "ID": "43",
        "Name": "S04P02-USARSALIENTE",
        "Alias": "USAR SALIENTES",
        "SensorID": 255,
        "SensorActive": false,
        "ScreenID": 26,
        "Cost": 25,
        "EnemyProbability": 0,
        "ResetEnemyProbability": 0,
        "DeathProbability": 1,
        "Description": "Comenzas a descender.\nAccion Exitosa: Descendiste lentamente hasta llegar a un descanso",
        "DescriptionActionFailed": "Comenzas a descender.\nAccion Fallida: El miedo te jugo una mala pasada y te soltaste de la soga. Muerte",
        "HideOnWaterLevelHigh": 0,
        "HideOnFearLevelHigh": 0,
        "HideWithFlashlightOff": 0
    },
    "44": {
        "ID": "44",
        "Name": "S04P02-NOUSARSALIENTES",
        "Alias": "NO USAR SALIENTES",
        "SensorID": 1,
        "SensorActive": true,
        "ScreenID": 26,
        "Cost": 10,
        "EnemyProbability": 0,
        "ResetEnemyProbability": 0,
        "DeathProbability": 85,
        "Description": "Comenzas a descender\nDescendiste rapidamente hasta llegar a un descanso",
        "DescriptionActionFailed": "Comenzas a descender\nSe te corto la soga. Muerte",
        "HideOnWaterLevelHigh": 0,
        "HideOnFearLevelHigh": 0,
        "HideWithFlashlightOff": 0
    },
    "45": {
        "ID": "45",
        "Name": "S04P03-EXPLORARZONA",
        "Alias": "EXPLORAR ZONA",
        "SensorID": 255,
        "SensorActive": false,
        "ScreenID": 255,
        "Cost": 10,
        "EnemyProbability": 0,
        "ResetEnemyProbability": 0,
        "DeathProbability": 1,
        "Description": "Exploras\nAccion Exitosa: No encontras nada destacado",
        "DescriptionActionFailed": "Exploras\nAccion Fallida: El miedo te jugo una mala pasada y te soltaste de la soga. Muerte",
        "HideOnWaterLevelHigh": 0,
        "HideOnFearLevelHigh": 0,
        "HideWithFlashlightOff": 0
    },
    "46": {
        "ID": "46",
        "Name": "S04P03-USARSALIENTES",
        "Alias": "USAR SALIENTES",
        "SensorID": 255,
        "SensorActive": false,
        "ScreenID": 27,
        "Cost": 25,
        "EnemyProbability": 0,
        "ResetEnemyProbability": 0,
        "DeathProbability": 1,
        "Description": "Comenzas a descender\nAccion Exitosa: Descendiste lentamente hasta llegar a un descanso",
        "DescriptionActionFailed": "Comenzas a descender\nAccion Fallida: El miedo te jugo una mala pasada y te soltaste de la soga. Muerte",
        "HideOnWaterLevelHigh": 0,
        "HideOnFearLevelHigh": 0,
        "HideWithFlashlightOff": 0
    },
    "47": {
        "ID": "47",
        "Name": "S04P03-NOUSARSALIENTES",
        "Alias": "NO USAR SALIENTES",
        "SensorID": 1,
        "SensorActive": true,
        "ScreenID": 27,
        "Cost": 10,
        "EnemyProbability": 0,
        "ResetEnemyProbability": 0,
        "DeathProbability": 85,
        "Description": "Comenzas a descender\nAccion Exitosa: Descendiste rapidamente hasta llegar a un descanso",
        "DescriptionActionFailed": "Comenzas a descender\nAccion Fallida: Se te corto la soga. Muerte",
        "HideOnWaterLevelHigh": 0,
        "HideOnFearLevelHigh": 0,
        "HideWithFlashlightOff": 0
    },
    "48": {
        "ID": "48",
        "Name": "S04P04-EXPLORARZONA",
        "Alias": "EXPLORAR ZONA",
        "SensorID": 255,
        "SensorActive": false,
        "ScreenID": 28,
        "Cost": 10,
        "EnemyProbability": 0,
        "ResetEnemyProbability": 0,
        "DeathProbability": 1,
        "Description": "Exploras\nAccion Exitosa: Encuentras algo",
        "DescriptionActionFailed": "Exploras\nAccion Fallida: El miedo te jugo una mala pasada y te soltaste de la soga. Muerte",
        "HideOnWaterLevelHigh": 0,
        "HideOnFearLevelHigh": 0,
        "HideWithFlashlightOff": 0
    },
    "49": {
        "ID": "49",
        "Name": "S04P04-USARSALIENTES",
        "Alias": "USAR SALIENTES",
        "SensorID": 255,
        "SensorActive": false,
        "ScreenID": 29,
        "Cost": 25,
        "EnemyProbability": 0,
        "ResetEnemyProbability": 0,
        "DeathProbability": 1,
        "Description": "Comenzas a descender\nDescendiste lentamente hasta tocar suelo firme.",
        "DescriptionActionFailed": "Comenzas a descender\nEl miedo te jugo una mala pasada y te soltaste de la soga. Muerte\n\n",
        "HideOnWaterLevelHigh": 0,
        "HideOnFearLevelHigh": 0,
        "HideWithFlashlightOff": 0
    },
    "50": {
        "ID": "50",
        "Name": "S04P04-NOUSARSALIENTES",
        "Alias": "NO USAR SALIENTES",
        "SensorID": 1,
        "SensorActive": true,
        "ScreenID": 29,
        "Cost": 10,
        "EnemyProbability": 0,
        "ResetEnemyProbability": 0,
        "DeathProbability": 85,
        "Description": "Comenzas a descender\nAccion Exitosa: Descendiste rapidamente hasta tocar suelo firme\n",
        "DescriptionActionFailed": "Comenzas a descender\nAccion Fallida: Se te corto la soga. Muerte",
        "HideOnWaterLevelHigh": 0,
        "HideOnFearLevelHigh": 0,
        "HideWithFlashlightOff": 0
    },
    "51": {
        "ID": "51",
        "Name": "S04P05-VOLVER",
        "Alias": "VOLVER",
        "SensorID": 255,
        "SensorActive": false,
        "ScreenID": 27,
        "Cost": 0,
        "EnemyProbability": 0,
        "ResetEnemyProbability": 0,
        "DeathProbability": 0,
        "Description": "Vuelve a pantalla anterior",
        "DescriptionActionFailed": "",
        "HideOnWaterLevelHigh": 0,
        "HideOnFearLevelHigh": 0,
        "HideWithFlashlightOff": 0
    },
    "52": {
        "ID": "52",
        "Name": "TERMINAR EL JUEGO",
        "SensorID": 4,
        "SensorActive": false,
        "ScreenID": 0,
        "Cost": 0,
        "Description": ""
    }
}